inertiassrprepper/__init__.py
inertiassrprepper/__version__.py
inertiassrprepper/main.py
inertiassrprepper/api/__init__.py
inertiassrprepper/api/claude.py
inertiassrprepper/cli/__init__.py
inertiassrprepper/cli/commands.py
inertiassrprepper/patterns/__init__.py
inertiassrprepper/patterns/ssr_patterns.py
inertiassrprepper/reporter/__init__.py
inertiassrprepper/reporter/reporter.py
inertiassrprepper/scanner/__init__.py
inertiassrprepper/scanner/scanner.py
inertiassrprepper/templates/html_report.py
inertiassrprepper/templates/html_simple.py
inertiassrprepper/utils/__init__.py
inertiassrprepper/utils/file_utils.py
inertiassrprepper-0.2.2.dist-info/METADATA
inertiassrprepper-0.2.2.dist-info/WHEEL
inertiassrprepper-0.2.2.dist-info/entry_points.txt
inertiassrprepper-0.2.2.dist-info/top_level.txt
inertiassrprepper-0.2.2.dist-info/RECORD
