Metadata-Version: 2.4
Name: inertiassrprepper
Version: 0.2.2
Summary: CLI tool to identify SSR compatibility issues in Laravel Inertia Vue applications
License: MIT
Requires-Python: >=3.12
Requires-Dist: typer>=0.9.0
Requires-Dist: rich>=13.7.0
Requires-Dist: anthropic>=0.18.1
Requires-Dist: tqdm>=4.66.1
Requires-Dist: pathspec>=0.12.1
Requires-Dist: jinja2>=3.0.0
